DE10_LITE_D8M_VIP_16/ip/EEE_IMGPROC/rgb_to_hsv.v
// module rgb_to_hsv(
//     input [7:0] green,
//     input [7:0] red,
//     input [7:0] blue,
//     output [8:0] hue,
//     output [7:0] min,
//     output [7:0] sat,
//     output [7:0] value
// );

// assign value = (red > green) ? ((red > blue) ? red[7:0] : blue[7:0]) : (green > blue) ? green[7:0] : blue[7:0];						
// assign min = (red < green)? ((red<blue) ? red[7:0] : blue[7:0]) : (green < blue) ? green [7:0] : blue[7:0];
// assign sat = (value - min)* 255 / value;
// assign hue = (red == green && red == blue) ? 0 :((value != red)? (value != green) ? (((240*((value - min)) + (60* (red - green)))/(value-min))>>1):
//                 ((120*(value-min)+60*(blue - red))/(value - min)>>1): 
//                 (blue < green) ? ((60*(green - blue)/(value - min))>>1): (((360*(value-min) +(60*(green - blue)))/(value - min))>>1));


// assign value = (red > green) ? ((red > blue) ? red[7:0] : blue[7:0]) : (green > blue) ? green[7:0] : blue[7:0];						
// assign min = (red < green)? ((red<blue) ? red[7:0] : blue[7:0]) : (green < blue) ? green [7:0] : blue[7:0];
// assign saturation = (value - min)* 255 / value;
// assign hue = (red == green && red == blue) ? 0 :((value != red)? (value != green) ? (((240*((value - min))+ (60* (red - green)))/(value-min))>>1):
//                 ((120*(value-min)+60*(blue - red))/(value - min)>>1): 
//                 (blue < green) ? ((60*(green - blue)/(value - min))>>1): (((360*(value-min) +(60*(green - blue)))/(value - min))>>1));

// endmodule
module  rgb_to_hsv(

                input                         clk,

                input                                   rst,         

                input          [7:0]            rgb_r,

                input          [7:0]            rgb_g,

                input          [7:0]            rgb_b,      

                output reg [8:0]                                                  hsv_h,

                output reg [7:0]                                                  hsv_s,

                output reg [7:0]                                                  hsv_v 
      
);

reg [7:0] top;//molecular

reg [13:0] top_60;//*60

reg [2:0] rgb_se;

reg [2:0] rgb_se_n;//

reg [7:0] max;//

reg [7:0] min;//

reg [7:0] max_min;//max - min

reg [7:0] hsv_s_m;

reg [7:0] max_n;

reg [7:0] division;//divisi

wire r_g, r_b, g_b;
//find max min 1----

assign r_g = (rgb_r > rgb_g)? 1'b1:1'b0;

assign r_b = (rgb_r > rgb_b)? 1'b1:1'b0;

assign g_b = (rgb_g > rgb_b)? 1'b1:1'b0;

always @ (posedge clk or negedge rst)

begin

                if (!rst)

                begin

                                max <= 8'd0;

                                min <= 8'd0;

                                top <= 8'd0;

                                rgb_se <= 3'b010;

                end

                else

                begin

                case ({r_g,r_b,g_b})

               

                3'b000:

                                                begin//b g r

                                                max <= rgb_b;

                                                min <= rgb_r;

                                                top <= rgb_g - rgb_r;//-

                                                rgb_se <= 3'b000;

                                                end

                3'b001:

                                                begin//g b r

                                                max <= rgb_g;

                                                min <= rgb_r;

                                                top <= rgb_b - rgb_r;//+

                                                rgb_se <= 3'b001;

                                                end

                3'b011:

                                                begin//g r b

                                                max <= rgb_g;

                                                min <= rgb_b;

                                                top <= rgb_r - rgb_b;//-

                                                rgb_se <= 3'b011;

                                                end

                3'b100:

                                                begin//b r g

                                                max <= rgb_b;

                                                min <= rgb_g;

                                                top <= rgb_r - rgb_g;//+

                                                rgb_se <= 3'b100;

                                                end

                3'b110:

                                                begin//r b g

                                                max <= rgb_r;

                                                min <= rgb_g;

                                                top <= rgb_b - rgb_g;//+

                                                rgb_se <= 3'b110;

                                                end

                3'b111:

                                                begin//r g b

                                                max <= rgb_r;

                                                min <= rgb_b;

                                                top <= rgb_g - rgb_b;//-

                                                rgb_se <= 3'b111;

                                                end

                default

                                                begin

                                                max <= 8'd0;

                                                min <= 8'd0;

                                                top <= 8'd0;

                                                rgb_se <= 3'b010;

                                                end

                endcase

end

end

// *60   max - min          2-----------------

always @ (posedge clk or negedge rst)

begin

                if (!rst)

                                begin

                                top_60 <= 14'd0;

                                rgb_se_n <= 3'b010;

                                max_min <= 8'd0;

                                max_n <= 8'd0;

                                end

                else

                                begin

                                top_60 <= {top,6'b000000} - {top,2'b00};//60 = 2^6 - 2^2

                                rgb_se_n <= rgb_se;

                                max_min <= max - min;

                                max_n <= max;

                                end

end

//   /(max - min)    3----------------------

always @ (*)

begin

                division = (max_min > 8'd0) ? top_60 / max_min : 8'd240;// Tenga en cuenta que max = min 

end

// + - 120 240 360

always @ (posedge clk or negedge rst)

begin

                if (!rst)

               

                                hsv_h <= 9'd0;

               

                else

                begin

                case (rgb_se_n)

               

                3'b000:

                                                //b g r

                                                hsv_h <= 9'd240 - division;//-

                                               

                3'b001:

                                                //g b r

                                                hsv_h <= 9'd120 + division;//+

                                               

                3'b011:

                                                //g r b

                                                hsv_h <= 9'd120 - division;//-

                                               

                3'b100:

                                                //b r g

                                                hsv_h <= 9'd240 + division;//+

                                               

                3'b110:

                                                //r b g

                                                hsv_h <= 9'd360 - division;//-

                                               

                                               

                3'b111:

                                                //r g b

                                                hsv_h <= division;//+

                                               

                default

                                                hsv_h <= 9'd0;

                endcase

end

end
//  s=(max - min)/max * 256

always @ (*)

begin

                hsv_s_m = (max_n > 8'd0)? {max_min[7:0],8'b00000000} / max_n : 8'd0;

end

always@(posedge clk or negedge rst)

begin

                if (!rst)

      hsv_s <= 8'd0;

                else

                hsv_s <= hsv_s_m;

end

//  hsv_v = max

always@(posedge clk or negedge rst)

begin

  if (!rst)

  hsv_v <= 8'd0;

  else

  hsv_v <= max_n;

end

// 3-------------------

endmodule

Vision/DE10_LITE_D8M_VIP_16/ip/EEE_IMGPROC/rgb_to_hsv_tb.v
module rgb_to_hsv_tb();
  logic clk;
  logic reset;
  logic[7:0] r,g,b,s,v, cmax, cmin;
  logic [8:0] h;
  


initial begin
  $dumpfile("testing.vcd");
  $dumpvars(0,rgb_to_hsv_tb);
  $display("running");
  clk = 0;
  r = 22;
  g = 48;
  b = 65;
  #10; 
  clk = ~clk;
  #10;
  clk = ~clk;
  #10; 
  clk = ~clk;
  #10;
  clk = ~clk;
  #10
  #10; 
  clk = ~clk;
  #10; 
  clk = ~clk;
  #10;
  clk = ~clk;
  #10; 
  clk = ~clk;
  #10;
  clk = ~clk;
  
  #10; 
  clk = ~clk;
  $display("h is %d, s is %d, v is %d", h,s,v);
  clk = 0;
  r = 235;
  g = 140;
  b = 238;
  #10; 
  clk = ~clk;
  reset = 1;
  #10;
  clk = ~clk;
  #10; 
  clk = ~clk;
  #10;
  clk = ~clk;
  #10
  #10; 
  clk = ~clk;
  #10;
  clk = ~clk;
  #10; 
  clk = ~clk;
  #10;
  clk = ~clk;
  #10; 
  clk = ~clk;
  #10;
  clk = ~clk;
  #10; 
  clk = ~clk;
  #10;
  clk = ~clk;
  #10;
  $display("h is %d, s is %d, v is %d", h,s,v);
  r = 238;
  g = 14;
  b = 89;
  #10; 
  clk = ~clk;
  #10;
  clk = ~clk;
  #10; 
  clk = ~clk;
  #10;
  clk = ~clk;
  #10;
  clk = ~clk;
  #10; 
  clk = ~clk;
  #10;
  clk = ~clk;
  #10
  $display("h is %d, s is %d, v is %d", h,s,v);
  r = 35;
  g = 70;
  b = 190;
  #10; 
  clk = ~clk;
  #10;
  clk = ~clk;
  #10; 
  clk = ~clk;
  #10;
  clk = ~clk;
  #10;
  clk = ~clk;
  #10; 
  clk = ~clk;
  #10;
  clk = ~clk;
  #10
  $display("h is %d, s is %d, v is %d", h,s,v);


end



  rgb_to_hsv dut(
      .clk(clk),
      .rst(reset),
      .rgb_r(r),
      .rgb_g(g),
      .rgb_b(b),
      .hsv_h(h),
      .hsv_s(s),
      .hsv_v(v)
  );

endmodule

Vision/DE10_LITE_D8M_VIP_16/ip/EEE_IMGPROC/testing.vcd
$date
	Mon Jun 20 12:10:54 2022
$end
$version
	Icarus Verilog
$end
$timescale
	1s
$end
$scope module rgb_to_hsv_tb $end
$var wire 8 ! v [7:0] $end
$var wire 8 " s [7:0] $end
$var wire 9 # h [8:0] $end
$var reg 8 $ b [7:0] $end
$var reg 1 % clk $end
$var reg 8 & g [7:0] $end
$var reg 8 ' r [7:0] $end
$var reg 1 ( reset $end
$scope module dut $end
$var wire 1 % clk $end
$var wire 8 ) rgb_b [7:0] $end
$var wire 8 * rgb_g [7:0] $end
$var wire 8 + rgb_r [7:0] $end
$var wire 1 ( rst $end
$var wire 1 , r_g $end
$var wire 1 - r_b $end
$var wire 1 . g_b $end
$var reg 8 / division [7:0] $end
$var reg 9 0 hsv_h [8:0] $end
$var reg 8 1 hsv_s [7:0] $end
$var reg 8 2 hsv_s_m [7:0] $end
$var reg 8 3 hsv_v [7:0] $end
$var reg 8 4 max [7:0] $end
$var reg 8 5 max_min [7:0] $end
$var reg 8 6 max_n [7:0] $end
$var reg 8 7 min [7:0] $end
$var reg 3 8 rgb_se [2:0] $end
$var reg 3 9 rgb_se_n [2:0] $end
$var reg 8 : top [7:0] $end
$var reg 14 ; top_60 [13:0] $end
$upscope $end
$upscope $end
$enddefinitions $end
#0
$dumpvars
bx ;
bx :
bx 9
bx 8
bx 7
bx 6
bx 5
bx 4
bx 3
bx 2
bx 1
bx 0
bx /
0.
0-
0,
b10110 +
b110000 *
b1000001 )
x(
b10110 '
b110000 &
0%
b1000001 $
bx #
bx "
bx !
$end
#10
b0 8
b11010 :
b10110 7
b1000001 4
b0 #
b0 0
1%
#20
0%
#30
b10101001 2
b100100 /
b1000001 6
b101011 5
b0 9
b11000011000 ;
1%
#40
0%
#60
b11001100 #
b11001100 0
b10101001 "
b10101001 1
b1000001 !
b1000001 3
1%
#70
0%
#80
1%
#90
0%
#100
1%
#110
1,
b11101110 $
b11101110 )
b10001100 &
b10001100 *
b11101011 '
b11101011 +
0%
#120
b100 8
b1011111 :
b10001100 7
b11101110 4
1(
1%
#130
0%
#140
b1101001 2
b111010 /
b11101110 6
b1100010 5
b100 9
b1011001000100 ;
1%
#150
0%
#170
b11101110 !
b11101110 3
b1101001 "
b1101001 1
b100101010 #
b100101010 0
1%
#180
0%
#190
1%
#200
0%
#210
1%
#220
0%
#230
1%
#240
0%
#250
1-
b1011001 $
b1011001 )
b1110 &
b1110 *
b11101110 '
b11101110 +
#260
b110 8
b1001011 :
b1110 7
1%
#270
0%
#280
b11110000 2
b10100 /
b11100000 5
b110 9
b1000110010100 ;
1%
#290
0%
#300
b11110000 "
b11110000 1
b101010100 #
b101010100 0
1%
#310
0%
#320
1%
#330
0,
0-
b10111110 $
b10111110 )
b1000110 &
b1000110 *
b100011 '
b100011 +
#340
0%
#350
b0 8
b100011 :
b100011 7
b10111110 4
1%
#360
0%
#370
b11010000 2
b1101 /
b10111110 6
b10011011 5
b0 9
b100000110100 ;
1%
#380
0%
#390
b10111110 !
b10111110 3
b11010000 "
b11010000 1
b11100011 #
b11100011 0
1%
